{
    "homepage": "https://github.com/qishibo/AnotherRedisDesktopManager",
    "version": "1.5.0",
    "description": "A faster, better and more stable redis desktop manager.",
    "checkver": "github",
    "license": "MIT",
    "shortcuts": [
        [
            "Another Redis Desktop Manager.exe",
            "Another Redis Desktop Manager"
        ]
    ],
    "autoupdate": {
        "architecture": {
            "64bit": {
                "url": "https://github.com/qishibo/AnotherRedisDesktopManager/releases/download/v$version/Another-Redis-Desktop-Manager.$version.exe#/dl.7z"
            }
        }
    },
    "architecture": {
        "64bit": {
            "url": "https://github.com/qishibo/AnotherRedisDesktopManager/releases/download/v1.5.0/Another-Redis-Desktop-Manager.1.5.0.exe#/dl.7z",
            "hash": "c0d46d520dd35a8bf471d83636087d24f7c0f743cb87c6bec9365a24e70a44ff",
            "pre_install": [
                "Expand-7zipArchive \"$dir\\`$PLUGINSDIR\\app-64.7z\" \"$dir\"",
                "Remove-Item \"$dir\\`$*\", \"$dir\\Uninst*\" -Recurse"
            ]
        }
    }
}
