{
    "version": "1.89",
    "description": "A simple one-file way to run various GGML models like LLAMA, ALPACA, VICUNA",
    "homepage": "https://github.com/LostRuins/koboldcpp",
    "license": "AGPL-3.0",
    "architecture": {
        "64bit": {
            "url": "https://github.com/LostRuins/koboldcpp/releases/download/v1.89/koboldcpp_cu12.exe",
            "hash": "21889220999ca6c3992f01cfcbb57cd03d20269aed0fa0002a694433c741da11"
        }
    },
    "bin": "koboldcpp_cu12.exe",
    "shortcuts": [
        [
            "koboldcpp_cu12.exe",
            "KoboldCpp"
        ]
    ],
    "checkver": "github",
    "autoupdate": {
        "architecture": {
            "64bit": {
                "url": "https://github.com/LostRuins/koboldcpp/releases/download/v$version/koboldcpp_cu12.exe"
            }
        }
    }
}
