{
    "version": "1.8.1",
    "description": "The cross-platform desktop GUI for rclone & S3",
    "homepage": "https://github.com/rclone-ui/rclone-ui",
    "license": "Apache-2.0",
    "shortcuts": [
        [
            "app.exe",
            "Rclone UI"
        ]
    ],
    "architecture": {
        "64bit": {
            "url": "https://github.com/rclone-ui/rclone-ui/releases/download/v1.8.1/Rclone.UI_1.8.1_x64-setup.exe#dl.7z",
            "hash": "9c433bfa1567a7c67c3db4b0654e2c7b41739c7d9661ca387b443b981472c749"
        }
    },
    "post_install": [
        "Remove-Item \"$dir\\`$PLUGINSDIR\" -Recurse -Force -ErrorAction SilentlyContinue",
        "Remove-Item \"$dir\\uninstall.exe\" -Force -ErrorAction SilentlyContinue"
    ],
    "checkver": {
        "github": "https://github.com/rclone-ui/rclone-ui"
    },
    "autoupdate": {
        "architecture": {
            "64bit": {
                "url": "https://github.com/rclone-ui/rclone-ui/releases/download/v$version/Rclone.UI_$version_x64-setup.exe#dl.7z"
            }
        }
    }
}
