{
    "homepage": "https://github.com/liriliri/rem",
    "license": "MIT",
    "version": "1.2.0",
    "description": "REM - A remote management tool",
    "architecture": {
        "64bit": {
            "url": "https://github.com/liriliri/rem/releases/download/v1.2.0/REM-1.2.0-win-x64.exe#/dl.7z",
            "hash": "44e4eee0ab937067036c4f9f2234bdc8fdb2142fbefbf0aacf9d94754706c518",
            "pre_install": [
                "Expand-7zipArchive \"$dir\\`$PLUGINSDIR\\app-64.7z\" \"$dir\"",
                "Remove-Item \"$dir\\`$PLUGINSDIR\", \"$dir\\`$R0\" -Recurse"
            ]
        }
    },
    "shortcuts": [
        [
            "REM.exe",
            "REM"
        ]
    ],
    "checkver": {
        "github": "https://github.com/liriliri/rem"
    },
    "autoupdate": {
        "architecture": {
            "64bit": {
                "url": "https://github.com/liriliri/rem/releases/download/v$version/REM-$version-win-x64.exe#/dl.7z"
            }
        }
    }
}
